rmux/__init__.py
rmux/tests/__init__.py
rmux/tests/base.py
rmux/tests/test_rmux.py
rmux-1.0.6.data/scripts/rmux
rmux-1.0.6.dist-info/LICENSE
rmux-1.0.6.dist-info/METADATA
rmux-1.0.6.dist-info/WHEEL
rmux-1.0.6.dist-info/pbr.json
rmux-1.0.6.dist-info/top_level.txt
rmux-1.0.6.dist-info/RECORD
