Metadata-Version: 2.1
Name: rmux
Version: 1.0.6
Summary: remux allows you to run your local project on multiple remote machines in parallel
Home-page: https://github.com/pycontribs/rmux/
Author: Sorin Sbarnea
Author-email: sorin.sbarnea@gmail.com
License: Apache
Platform: any
Classifier: Intended Audience :: Information Technology
Classifier: Intended Audience :: System Administrators
Classifier: License :: OSI Approved :: Apache Software License
Classifier: Operating System :: POSIX :: Linux
Classifier: Programming Language :: Python
Classifier: Programming Language :: Python :: 2
Classifier: Programming Language :: Python :: 2.7
Classifier: Programming Language :: Python :: 3
Classifier: Programming Language :: Python :: 3.5
Classifier: Programming Language :: Python :: 3.6
Classifier: Programming Language :: Python :: 3.7
Classifier: Programming Language :: Python :: 3.8
Requires-Dist: pbr (>=2.0)
